robo_test_suite_appian/__init__.py
robo_test_suite_appian/utils/__init__.py
robo_test_suite_appian/utils/components/ButtonUtils.py
robo_test_suite_appian/utils/components/ComponentUtils.py
robo_test_suite_appian/utils/components/DateUtils.py
robo_test_suite_appian/utils/components/DropdownUtils.py
robo_test_suite_appian/utils/components/InputUtils.py
robo_test_suite_appian/utils/components/LabelUtils.py
robo_test_suite_appian/utils/components/LinkUtils.py
robo_test_suite_appian/utils/components/TabUtils.py
robo_test_suite_appian/utils/components/TableUtils.py
robo_test_suite_appian/utils/components/__init__.py
robo_test_suite_appian/utils/controllers/ComponentDriver.py
robo_test_suite_appian/utils/controllers/__init__.py
robo_test_suite_appian/utils/exceptions/MyCustomError.py
robo_test_suite_appian/utils/exceptions/__init__.py
robo_test_suite_appian-0.0.1.dist-info/licenses/LICENSE
robo_test_suite_appian-0.0.1.dist-info/METADATA
robo_test_suite_appian-0.0.1.dist-info/WHEEL
robo_test_suite_appian-0.0.1.dist-info/top_level.txt
robo_test_suite_appian-0.0.1.dist-info/RECORD
