Metadata-Version: 2.4
Name: robo_test_suite_appian
Version: 0.0.1
Summary: Automate your Appin code testing with Python. Boost quality, save time.
Home-page: https://github.com/dinilmithra/robo_test_suite_appian.git
Author: Dinil Mithra
Author-email: dinilmithra@mailme@gmail.com
Classifier: Programming Language :: Python :: 3
Classifier: Operating System :: OS Independent
Requires-Python: >=3.12
License-File: LICENSE
Requires-Dist: selenium>=4.34.0
Dynamic: author
Dynamic: author-email
Dynamic: classifier
Dynamic: description
Dynamic: description-content-type
Dynamic: home-page
Dynamic: license-file
Dynamic: requires-dist
Dynamic: requires-python
Dynamic: summary
